{"business": {"id": "biz_0447", "name": "Reef Restaurant", "type": "a", "sector": "high_freq_low_ticket_food", "archetype": "high_freq_low_ticket_food", "loan_pipeline": "sme"}, "summary": {"business_id": "biz_0447", "period": "2024-10-01 to 2024-12-30", "total_transactions": 8391, "total_revenue_sar": 280414.85, "avg_daily_revenue_sar": 3115.72, "avg_daily_transactions": 92.2, "avg_energy_kwh": 91.97, "avg_efficiency_score": 0.6262, "green_days": ["2024-11-25", "2024-12-14", "2024-12-23"], "payment_method_breakdown": {"mada": 0.6452, "cash": 0.2031, "credit_card": 0.1517}}, "dscr": {"business_id": "biz_0447", "dscr_score": 3.9085, "risk_tier": "very_low", "approved_credit_limit_sar": 416000.0, "dynamic_credit_limit": {"adjusted_credit_limit": 416000.0, "trend_direction": "steady", "adjustment_multiplier": 1.0}, "expense_ratio": 0.77, "expense_source": "ai_derived", "archetype_description": "high_freq_low_ticket_food", "net_operating_income_sar": 21557.53, "interest_rate_base": 0.065, "final_interest_rate": 0.060000000000000005, "sustainability_eligible": true, "revenue_metrics": {"total_revenue": 280414.85, "avg_daily_revenue": 3115.72, "revenue_trend": "steady"}, "transition_readiness": {"decision": "approve", "blocking_reasons": [], "gates_passed": ["revenue_verified", "archetype_classified", "dscr_sufficient"], "recommended_pipeline": "sme_loan"}}, "fraud": {"business_id": "biz_0447", "overall_status": "clean", "fraud_score": 20, "approval_frozen": false, "anomalies": [], "checks_passed": ["amount_range", "hour_pattern", "payment_method"], "reasons": []}, "forecast": {"summary": {"trend_direction": "steady", "avg_predicted_revenue": 3115.72, "confidence": 0.4434}, "series": [{"date": "2025-01-01", "predicted_revenue": 3115.72, "upper_bound": 3583.08, "lower_bound": 2648.36}, {"date": "2025-01-02", "predicted_revenue": 3115.72, "upper_bound": 3583.08, "lower_bound": 2648.36}, {"date": "2025-01-03", "predicted_revenue": 3115.72, "upper_bound": 3583.08, "lower_bound": 2648.36}, {"date": "2025-01-04", "predicted_revenue": 3115.72, "upper_bound": 3583.08, "lower_bound": 2648.36}, {"date": "2025-01-05", "predicted_revenue": 3115.72, "upper_bound": 3583.08, "lower_bound": 2648.36}, {"date": "2025-01-06", "predicted_revenue": 3115.72, "upper_bound": 3583.08, "lower_bound": 2648.36}, {"date": "2025-01-07", "predicted_revenue": 3115.72, "upper_bound": 3583.08, "lower_bound": 2648.36}, {"date": "2025-01-08", "predicted_revenue": 3115.72, "upper_bound": 3583.08, "lower_bound": 2648.36}, {"date": "2025-01-09", "predicted_revenue": 3115.72, "upper_bound": 3583.08, "lower_bound": 2648.36}, {"date": "2025-01-10", "predicted_revenue": 3115.72, "upper_bound": 3583.08, "lower_bound": 2648.36}, {"date": "2025-01-11", "predicted_revenue": 3115.72, "upper_bound": 3583.08, "lower_bound": 2648.36}, {"date": "2025-01-12", "predicted_revenue": 3115.72, "upper_bound": 3583.08, "lower_bound": 2648.36}, {"date": "2025-01-13", "predicted_revenue": 3115.72, "upper_bound": 3583.08, "lower_bound": 2648.36}, {"date": "2025-01-14", "predicted_revenue": 3115.72, "upper_bound": 3583.08, "lower_bound": 2648.36}, {"date": "2025-01-15", "predicted_revenue": 3115.72, "upper_bound": 3583.08, "lower_bound": 2648.36}, {"date": "2025-01-16", "predicted_revenue": 3115.72, "upper_bound": 3583.08, "lower_bound": 2648.36}, {"date": "2025-01-17", "predicted_revenue": 3115.72, "upper_bound": 3583.08, "lower_bound": 2648.36}, {"date": "2025-01-18", "predicted_revenue": 3115.72, "upper_bound": 3583.08, "lower_bound": 2648.36}, {"date": "2025-01-19", "predicted_revenue": 3115.72, "upper_bound": 3583.08, "lower_bound": 2648.36}, {"date": "2025-01-20", "predicted_revenue": 3115.72, "upper_bound": 3583.08, "lower_bound": 2648.36}, {"date": "2025-01-21", "predicted_revenue": 3115.72, "upper_bound": 3583.08, "lower_bound": 2648.36}, {"date": "2025-01-22", "predicted_revenue": 3115.72, "upper_bound": 3583.08, "lower_bound": 2648.36}, {"date": "2025-01-23", "predicted_revenue": 3115.72, "upper_bound": 3583.08, "lower_bound": 2648.36}, {"date": "2025-01-24", "predicted_revenue": 3115.72, "upper_bound": 3583.08, "lower_bound": 2648.36}, {"date": "2025-01-25", "predicted_revenue": 3115.72, "upper_bound": 3583.08, "lower_bound": 2648.36}, {"date": "2025-01-26", "predicted_revenue": 3115.72, "upper_bound": 3583.08, "lower_bound": 2648.36}, {"date": "2025-01-27", "predicted_revenue": 3115.72, "upper_bound": 3583.08, "lower_bound": 2648.36}, {"date": "2025-01-28", "predicted_revenue": 3115.72, "upper_bound": 3583.08, "lower_bound": 2648.36}, {"date": "2025-01-29", "predicted_revenue": 3115.72, "upper_bound": 3583.08, "lower_bound": 2648.36}, {"date": "2025-01-30", "predicted_revenue": 3115.72, "upper_bound": 3583.08, "lower_bound": 2648.36}]}, "recent_transactions": [{"transaction_id": "biz_0447-008349", "timestamp": "2024-12-30 17:43:37", "amount_sar": 10.57, "payment_method": "mada"}, {"transaction_id": "biz_0447-008362", "timestamp": "2024-12-30 17:57:32", "amount_sar": 36.4, "payment_method": "credit_card"}, {"transaction_id": "biz_0447-008317", "timestamp": "2024-12-30 18:14:57", "amount_sar": 49.31, "payment_method": "mada"}, {"transaction_id": "biz_0447-008370", "timestamp": "2024-12-30 18:26:54", "amount_sar": 18.46, "payment_method": "mada"}, {"transaction_id": "biz_0447-008348", "timestamp": "2024-12-30 18:52:04", "amount_sar": 25.12, "payment_method": "cash"}, {"transaction_id": "biz_0447-008384", "timestamp": "2024-12-30 18:56:53", "amount_sar": 20.42, "payment_method": "cash"}, {"transaction_id": "biz_0447-008352", "timestamp": "2024-12-30 18:57:42", "amount_sar": 53.69, "payment_method": "cash"}, {"transaction_id": "biz_0447-008304", "timestamp": "2024-12-30 20:43:11", "amount_sar": 69.92, "payment_method": "mada"}, {"transaction_id": "biz_0447-008356", "timestamp": "2024-12-30 22:34:11", "amount_sar": 17.42, "payment_method": "mada"}, {"transaction_id": "biz_0447-008299", "timestamp": "2024-12-30 23:06:09", "amount_sar": 24.33, "payment_method": "mada"}], "energy_trend": [{"date": "2024-12-24", "total_kwh": 97.28, "peak_hour_kwh": 57.64, "off_peak_kwh": 39.64, "energy_efficiency_score": 0.6801}, {"date": "2024-12-25", "total_kwh": 94.73, "peak_hour_kwh": 55.24, "off_peak_kwh": 39.49, "energy_efficiency_score": 0.4713}, {"date": "2024-12-26", "total_kwh": 100.54, "peak_hour_kwh": 66.83, "off_peak_kwh": 33.71, "energy_efficiency_score": 0.6574}, {"date": "2024-12-27", "total_kwh": 99.62, "peak_hour_kwh": 69.99, "off_peak_kwh": 29.63, "energy_efficiency_score": 0.576}, {"date": "2024-12-28", "total_kwh": 97.92, "peak_hour_kwh": 64.22, "off_peak_kwh": 33.7, "energy_efficiency_score": 0.7871}, {"date": "2024-12-29", "total_kwh": 78.2, "peak_hour_kwh": 54.69, "off_peak_kwh": 23.51, "energy_efficiency_score": 0.4873}, {"date": "2024-12-30", "total_kwh": 94.13, "peak_hour_kwh": 51.85, "off_peak_kwh": 42.28, "energy_efficiency_score": 0.6005}]}