{"business": {"id": "biz_0433", "name": "Rami Superstore", "type": "b", "sector": "high_freq_mid_ticket_retail", "archetype": "high_freq_mid_ticket_retail", "loan_pipeline": "sme"}, "summary": {"business_id": "biz_0433", "period": "2024-10-01 to 2024-12-30", "total_transactions": 21004, "total_revenue_sar": 1906972.94, "avg_daily_revenue_sar": 21188.59, "avg_daily_transactions": 230.8, "avg_energy_kwh": 198.62, "avg_efficiency_score": 0.6537, "green_days": ["2024-10-14", "2024-12-11", "2024-12-25"], "payment_method_breakdown": {"mada": 0.4966, "cash": 0.4036, "credit_card": 0.0997}}, "dscr": {"business_id": "biz_0433", "dscr_score": 3.2288, "risk_tier": "very_low", "approved_credit_limit_sar": 2829026.0, "dynamic_credit_limit": {"adjusted_credit_limit": 2829026.0, "trend_direction": "steady", "adjustment_multiplier": 1.0}, "expense_ratio": 0.81, "expense_source": "ai_derived", "archetype_description": "high_freq_mid_ticket_retail", "net_operating_income_sar": 121106.75, "interest_rate_base": 0.065, "final_interest_rate": 0.060000000000000005, "sustainability_eligible": true, "revenue_metrics": {"total_revenue": 1906972.94, "avg_daily_revenue": 21188.59, "revenue_trend": "steady"}, "transition_readiness": {"decision": "approve", "blocking_reasons": [], "gates_passed": ["revenue_verified", "archetype_classified", "dscr_sufficient"], "recommended_pipeline": "sme_loan"}}, "fraud": {"business_id": "biz_0433", "overall_status": "flagged", "fraud_score": 41, "approval_frozen": false, "anomalies": [], "checks_passed": ["amount_range", "hour_pattern", "payment_method"], "reasons": ["Behavioral anomaly detected"]}, "forecast": {"summary": {"trend_direction": "steady", "avg_predicted_revenue": 21188.59, "confidence": 0.303}, "series": [{"date": "2025-07-01", "predicted_revenue": 18831.06, "upper_bound": 21090.78, "lower_bound": 16571.33}, {"date": "2025-07-02", "predicted_revenue": 18605.65, "upper_bound": 20912.76, "lower_bound": 16298.55}, {"date": "2025-07-03", "predicted_revenue": 27577.97, "upper_bound": 31107.95, "lower_bound": 24047.99}, {"date": "2025-07-04", "predicted_revenue": 29388.03, "upper_bound": 33267.25, "lower_bound": 25508.81}, {"date": "2025-07-05", "predicted_revenue": 20316.57, "upper_bound": 23079.63, "lower_bound": 17553.52}, {"date": "2025-07-06", "predicted_revenue": 14878.61, "upper_bound": 16961.62, "lower_bound": 12795.61}, {"date": "2025-07-07", "predicted_revenue": 16700.01, "upper_bound": 19104.81, "lower_bound": 14295.21}, {"date": "2025-07-08", "predicted_revenue": 18088.87, "upper_bound": 20766.03, "lower_bound": 15411.72}, {"date": "2025-07-09", "predicted_revenue": 21491.12, "upper_bound": 24757.77, "lower_bound": 18224.47}, {"date": "2025-07-10", "predicted_revenue": 24818.28, "upper_bound": 28689.93, "lower_bound": 20946.63}, {"date": "2025-07-11", "predicted_revenue": 29749.62, "upper_bound": 34509.56, "lower_bound": 24989.68}, {"date": "2025-07-12", "predicted_revenue": 25846.36, "upper_bound": 30085.16, "lower_bound": 21607.56}, {"date": "2025-07-13", "predicted_revenue": 14083.85, "upper_bound": 16449.94, "lower_bound": 11717.77}, {"date": "2025-07-14", "predicted_revenue": 15037.24, "upper_bound": 17623.64, "lower_bound": 12450.83}, {"date": "2025-07-15", "predicted_revenue": 18379.41, "upper_bound": 21614.18, "lower_bound": 15144.63}, {"date": "2025-07-16", "predicted_revenue": 18644.88, "upper_bound": 22000.96, "lower_bound": 15288.81}, {"date": "2025-07-17", "predicted_revenue": 28170.15, "upper_bound": 33353.46, "lower_bound": 22986.85}, {"date": "2025-07-18", "predicted_revenue": 30181.81, "upper_bound": 35855.99, "lower_bound": 24507.63}, {"date": "2025-07-19", "predicted_revenue": 23786.84, "upper_bound": 28353.91, "lower_bound": 19219.76}, {"date": "2025-07-20", "predicted_revenue": 15266.75, "upper_bound": 18259.04, "lower_bound": 12274.47}, {"date": "2025-07-21", "predicted_revenue": 15039.07, "upper_bound": 18046.88, "lower_bound": 12031.25}, {"date": "2025-07-22", "predicted_revenue": 18685.04, "upper_bound": 22496.78, "lower_bound": 14873.29}, {"date": "2025-07-23", "predicted_revenue": 20377.35, "upper_bound": 24615.84, "lower_bound": 16138.86}, {"date": "2025-07-24", "predicted_revenue": 27797.88, "upper_bound": 33691.03, "lower_bound": 21904.73}, {"date": "2025-07-25", "predicted_revenue": 28173.19, "upper_bound": 34258.6, "lower_bound": 22087.78}, {"date": "2025-07-26", "predicted_revenue": 21551.92, "upper_bound": 26293.35, "lower_bound": 16810.5}, {"date": "2025-07-27", "predicted_revenue": 14350.45, "upper_bound": 17564.96, "lower_bound": 11135.95}, {"date": "2025-07-28", "predicted_revenue": 16075.72, "upper_bound": 19740.99, "lower_bound": 12410.46}, {"date": "2025-07-29", "predicted_revenue": 17129.29, "upper_bound": 21103.28, "lower_bound": 13155.29}, {"date": "2025-07-30", "predicted_revenue": 18509.57, "upper_bound": 22877.83, "lower_bound": 14141.31}]}, "recent_transactions": [{"transaction_id": "biz_0433-020783", "timestamp": "2024-12-30 22:02:53", "amount_sar": 276.59, "payment_method": "mada"}, {"transaction_id": "biz_0433-020803", "timestamp": "2024-12-30 22:11:40", "amount_sar": 32.35, "payment_method": "cash"}, {"transaction_id": "biz_0433-020974", "timestamp": "2024-12-30 22:28:50", "amount_sar": 11.07, "payment_method": "mada"}, {"transaction_id": "biz_0433-020800", "timestamp": "2024-12-30 22:40:02", "amount_sar": 50.62, "payment_method": "cash"}, {"transaction_id": "biz_0433-020753", "timestamp": "2024-12-30 22:54:40", "amount_sar": 118.47, "payment_method": "mada"}, {"transaction_id": "biz_0433-020920", "timestamp": "2024-12-30 23:04:47", "amount_sar": 18.18, "payment_method": "cash"}, {"transaction_id": "biz_0433-020976", "timestamp": "2024-12-30 23:20:35", "amount_sar": 98.3, "payment_method": "cash"}, {"transaction_id": "biz_0433-020965", "timestamp": "2024-12-30 23:27:37", "amount_sar": 31.38, "payment_method": "cash"}, {"transaction_id": "biz_0433-020779", "timestamp": "2024-12-30 23:47:52", "amount_sar": 403.63, "payment_method": "mada"}, {"transaction_id": "biz_0433-020815", "timestamp": "2024-12-30 23:58:45", "amount_sar": 113.04, "payment_method": "cash"}], "energy_trend": [{"date": "2024-12-24", "total_kwh": 191.24, "peak_hour_kwh": 126.56, "off_peak_kwh": 64.68, "energy_efficiency_score": 0.7357}, {"date": "2024-12-25", "total_kwh": 217.02, "peak_hour_kwh": 136.83, "off_peak_kwh": 80.19, "energy_efficiency_score": 0.8537}, {"date": "2024-12-26", "total_kwh": 213.53, "peak_hour_kwh": 127.93, "off_peak_kwh": 85.6, "energy_efficiency_score": 0.8251}, {"date": "2024-12-27", "total_kwh": 168.04, "peak_hour_kwh": 100.99, "off_peak_kwh": 67.05, "energy_efficiency_score": 0.8208}, {"date": "2024-12-28", "total_kwh": 151.71, "peak_hour_kwh": 86.23, "off_peak_kwh": 65.48, "energy_efficiency_score": 0.4935}, {"date": "2024-12-29", "total_kwh": 226.14, "peak_hour_kwh": 134.87, "off_peak_kwh": 91.27, "energy_efficiency_score": 0.7631}, {"date": "2024-12-30", "total_kwh": 187.64, "peak_hour_kwh": 133.12, "off_peak_kwh": 54.52, "energy_efficiency_score": 0.4051}]}