{"business": {"id": "biz_0114", "name": "Manal Restaurant", "type": "a", "sector": "high_freq_low_ticket_food", "archetype": "high_freq_low_ticket_food", "loan_pipeline": "sme"}, "summary": {"business_id": "biz_0114", "period": "2024-10-01 to 2024-12-30", "total_transactions": 9190, "total_revenue_sar": 274319.57, "avg_daily_revenue_sar": 3014.5, "avg_daily_transactions": 101.0, "avg_energy_kwh": 92.87, "avg_efficiency_score": 0.6499, "green_days": ["2024-10-17", "2024-11-03", "2024-11-17", "2024-11-26", "2024-11-28"], "payment_method_breakdown": {"mada": 0.6515, "cash": 0.1975, "credit_card": 0.151}}, "dscr": {"business_id": "biz_0114", "dscr_score": 3.9085, "risk_tier": "very_low", "approved_credit_limit_sar": 406958.0, "dynamic_credit_limit": {"adjusted_credit_limit": 406958.0, "trend_direction": "steady", "adjustment_multiplier": 1.0}, "expense_ratio": 0.77, "expense_source": "ai_derived", "archetype_description": "high_freq_low_ticket_food", "net_operating_income_sar": 21088.94, "interest_rate_base": 0.065, "final_interest_rate": 0.060000000000000005, "sustainability_eligible": true, "revenue_metrics": {"total_revenue": 274319.57, "avg_daily_revenue": 3014.5, "revenue_trend": "steady"}, "transition_readiness": {"decision": "approve", "blocking_reasons": [], "gates_passed": ["revenue_verified", "archetype_classified", "dscr_sufficient"], "recommended_pipeline": "sme_loan"}}, "fraud": {"business_id": "biz_0114", "overall_status": "clean", "fraud_score": 2, "approval_frozen": false, "anomalies": [], "checks_passed": ["amount_range", "hour_pattern", "payment_method"], "reasons": []}, "forecast": {"summary": {"trend_direction": "steady", "avg_predicted_revenue": 3014.5, "confidence": 0.3707}, "series": [{"date": "2025-07-01", "predicted_revenue": 2803.24, "upper_bound": 3139.63, "lower_bound": 2466.85}, {"date": "2025-07-02", "predicted_revenue": 3001.95, "upper_bound": 3374.19, "lower_bound": 2629.71}, {"date": "2025-07-03", "predicted_revenue": 3688.23, "upper_bound": 4160.32, "lower_bound": 3216.14}, {"date": "2025-07-04", "predicted_revenue": 4088.33, "upper_bound": 4627.99, "lower_bound": 3548.67}, {"date": "2025-07-05", "predicted_revenue": 3186.64, "upper_bound": 3620.03, "lower_bound": 2753.26}, {"date": "2025-07-06", "predicted_revenue": 1751.09, "upper_bound": 1996.25, "lower_bound": 1505.94}, {"date": "2025-07-07", "predicted_revenue": 2232.54, "upper_bound": 2554.02, "lower_bound": 1911.05}, {"date": "2025-07-08", "predicted_revenue": 2837.77, "upper_bound": 3257.76, "lower_bound": 2417.78}, {"date": "2025-07-09", "predicted_revenue": 3057.57, "upper_bound": 3522.32, "lower_bound": 2592.82}, {"date": "2025-07-10", "predicted_revenue": 4392.47, "upper_bound": 5077.7, "lower_bound": 3707.24}, {"date": "2025-07-11", "predicted_revenue": 4244.38, "upper_bound": 4923.48, "lower_bound": 3565.28}, {"date": "2025-07-12", "predicted_revenue": 3313.11, "upper_bound": 3856.46, "lower_bound": 2769.76}, {"date": "2025-07-13", "predicted_revenue": 1699.09, "upper_bound": 1984.54, "lower_bound": 1413.64}, {"date": "2025-07-14", "predicted_revenue": 2624.42, "upper_bound": 3075.82, "lower_bound": 2173.02}, {"date": "2025-07-15", "predicted_revenue": 2714.69, "upper_bound": 3192.48, "lower_bound": 2236.91}, {"date": "2025-07-16", "predicted_revenue": 3515.46, "upper_bound": 4148.24, "lower_bound": 2882.68}, {"date": "2025-07-17", "predicted_revenue": 3960.67, "upper_bound": 4689.44, "lower_bound": 3231.91}, {"date": "2025-07-18", "predicted_revenue": 4537.46, "upper_bound": 5390.5, "lower_bound": 3684.42}, {"date": "2025-07-19", "predicted_revenue": 3334.01, "upper_bound": 3974.14, "lower_bound": 2693.88}, {"date": "2025-07-20", "predicted_revenue": 1763.8, "upper_bound": 2109.5, "lower_bound": 1418.09}, {"date": "2025-07-21", "predicted_revenue": 2280.18, "upper_bound": 2736.22, "lower_bound": 1824.14}, {"date": "2025-07-22", "predicted_revenue": 2998.91, "upper_bound": 3610.69, "lower_bound": 2387.13}, {"date": "2025-07-23", "predicted_revenue": 3095.9, "upper_bound": 3739.85, "lower_bound": 2451.96}, {"date": "2025-07-24", "predicted_revenue": 3878.32, "upper_bound": 4700.52, "lower_bound": 3056.11}, {"date": "2025-07-25", "predicted_revenue": 3977.7, "upper_bound": 4836.88, "lower_bound": 3118.51}, {"date": "2025-07-26", "predicted_revenue": 3192.95, "upper_bound": 3895.4, "lower_bound": 2490.5}, {"date": "2025-07-27", "predicted_revenue": 1707.88, "upper_bound": 2090.45, "lower_bound": 1325.32}, {"date": "2025-07-28", "predicted_revenue": 2500.54, "upper_bound": 3070.66, "lower_bound": 1930.42}, {"date": "2025-07-29", "predicted_revenue": 2830.43, "upper_bound": 3487.1, "lower_bound": 2173.77}, {"date": "2025-07-30", "predicted_revenue": 2859.09, "upper_bound": 3533.84, "lower_bound": 2184.34}]}, "recent_transactions": [{"transaction_id": "biz_0114-009153", "timestamp": "2024-12-30 18:48:13", "amount_sar": 31.83, "payment_method": "mada"}, {"transaction_id": "biz_0114-009147", "timestamp": "2024-12-30 18:56:23", "amount_sar": 36.8, "payment_method": "mada"}, {"transaction_id": "biz_0114-009138", "timestamp": "2024-12-30 18:58:04", "amount_sar": 14.4, "payment_method": "mada"}, {"transaction_id": "biz_0114-009169", "timestamp": "2024-12-30 19:24:30", "amount_sar": 26.64, "payment_method": "mada"}, {"transaction_id": "biz_0114-009115", "timestamp": "2024-12-30 19:26:12", "amount_sar": 24.97, "payment_method": "mada"}, {"transaction_id": "biz_0114-009168", "timestamp": "2024-12-30 19:34:12", "amount_sar": 19.9, "payment_method": "mada"}, {"transaction_id": "biz_0114-009145", "timestamp": "2024-12-30 19:54:15", "amount_sar": 30.07, "payment_method": "cash"}, {"transaction_id": "biz_0114-009167", "timestamp": "2024-12-30 20:27:34", "amount_sar": 33.52, "payment_method": "mada"}, {"transaction_id": "biz_0114-009152", "timestamp": "2024-12-30 20:36:42", "amount_sar": 35.07, "payment_method": "mada"}, {"transaction_id": "biz_0114-009120", "timestamp": "2024-12-30 22:21:07", "amount_sar": 14.31, "payment_method": "mada"}], "energy_trend": [{"date": "2024-12-24", "total_kwh": 108.76, "peak_hour_kwh": 71.53, "off_peak_kwh": 37.23, "energy_efficiency_score": 0.6159}, {"date": "2024-12-25", "total_kwh": 76.86, "peak_hour_kwh": 52.2, "off_peak_kwh": 24.66, "energy_efficiency_score": 0.7922}, {"date": "2024-12-26", "total_kwh": 104.47, "peak_hour_kwh": 57.28, "off_peak_kwh": 47.19, "energy_efficiency_score": 0.6275}, {"date": "2024-12-27", "total_kwh": 84.45, "peak_hour_kwh": 52.71, "off_peak_kwh": 31.74, "energy_efficiency_score": 0.6165}, {"date": "2024-12-28", "total_kwh": 97.29, "peak_hour_kwh": 53.19, "off_peak_kwh": 44.1, "energy_efficiency_score": 0.6689}, {"date": "2024-12-29", "total_kwh": 73.54, "peak_hour_kwh": 48.92, "off_peak_kwh": 24.62, "energy_efficiency_score": 0.4636}, {"date": "2024-12-30", "total_kwh": 76.5, "peak_hour_kwh": 45.64, "off_peak_kwh": 30.86, "energy_efficiency_score": 0.4121}]}