{"business": {"id": "biz_0223", "name": "Luban Superstore", "type": "b", "sector": "high_freq_mid_ticket_retail", "archetype": "high_freq_mid_ticket_retail", "loan_pipeline": "sme"}, "summary": {"business_id": "biz_0223", "period": "2024-10-01 to 2024-12-30", "total_transactions": 21082, "total_revenue_sar": 1953788.78, "avg_daily_revenue_sar": 21952.68, "avg_daily_transactions": 231.7, "avg_energy_kwh": 188.2, "avg_efficiency_score": 0.6658, "green_days": ["2024-10-17", "2024-12-07", "2024-12-15", "2024-12-28"], "payment_method_breakdown": {"mada": 0.5045, "cash": 0.3978, "credit_card": 0.0977}}, "dscr": {"business_id": "biz_0223", "dscr_score": 3.2288, "risk_tier": "very_low", "approved_credit_limit_sar": 2898478.0, "dynamic_credit_limit": {"adjusted_credit_limit": 2898478.0, "trend_direction": "growing", "adjustment_multiplier": 1.1}, "expense_ratio": 0.81, "expense_source": "ai_derived", "archetype_description": "high_freq_mid_ticket_retail", "net_operating_income_sar": 124079.9, "interest_rate_base": 0.065, "final_interest_rate": 0.060000000000000005, "sustainability_eligible": true, "revenue_metrics": {"total_revenue": 1953788.78, "avg_daily_revenue": 21952.68, "revenue_trend": "growing"}, "transition_readiness": {"decision": "approve", "blocking_reasons": [], "gates_passed": ["revenue_verified", "archetype_classified", "dscr_sufficient"], "recommended_pipeline": "sme_loan"}}, "fraud": {"business_id": "biz_0223", "overall_status": "clean", "fraud_score": 6, "approval_frozen": false, "anomalies": [], "checks_passed": ["amount_range", "hour_pattern", "payment_method"], "reasons": []}, "forecast": {"summary": {"trend_direction": "growing", "avg_predicted_revenue": 21952.68, "confidence": 0.1817}, "series": [{"date": "2025-07-01", "predicted_revenue": 17545.0, "upper_bound": 19650.4, "lower_bound": 15439.6}, {"date": "2025-07-02", "predicted_revenue": 21503.33, "upper_bound": 24169.74, "lower_bound": 18836.91}, {"date": "2025-07-03", "predicted_revenue": 31958.6, "upper_bound": 36049.3, "lower_bound": 27867.9}, {"date": "2025-07-04", "predicted_revenue": 29786.02, "upper_bound": 33717.78, "lower_bound": 25854.27}, {"date": "2025-07-05", "predicted_revenue": 23474.51, "upper_bound": 26667.05, "lower_bound": 20281.98}, {"date": "2025-07-06", "predicted_revenue": 14979.19, "upper_bound": 17076.28, "lower_bound": 12882.1}, {"date": "2025-07-07", "predicted_revenue": 16080.17, "upper_bound": 18395.72, "lower_bound": 13764.63}, {"date": "2025-07-08", "predicted_revenue": 21142.08, "upper_bound": 24271.11, "lower_bound": 18013.05}, {"date": "2025-07-09", "predicted_revenue": 22451.68, "upper_bound": 25864.33, "lower_bound": 19039.02}, {"date": "2025-07-10", "predicted_revenue": 30604.75, "upper_bound": 35379.09, "lower_bound": 25830.41}, {"date": "2025-07-11", "predicted_revenue": 30378.8, "upper_bound": 35239.41, "lower_bound": 25518.19}, {"date": "2025-07-12", "predicted_revenue": 23905.94, "upper_bound": 27826.51, "lower_bound": 19985.36}, {"date": "2025-07-13", "predicted_revenue": 16006.98, "upper_bound": 18696.15, "lower_bound": 13317.8}, {"date": "2025-07-14", "predicted_revenue": 16506.2, "upper_bound": 19345.26, "lower_bound": 13667.13}, {"date": "2025-07-15", "predicted_revenue": 18698.58, "upper_bound": 21989.53, "lower_bound": 15407.63}, {"date": "2025-07-16", "predicted_revenue": 23306.15, "upper_bound": 27501.26, "lower_bound": 19111.05}, {"date": "2025-07-17", "predicted_revenue": 33410.69, "upper_bound": 39558.25, "lower_bound": 27263.12}, {"date": "2025-07-18", "predicted_revenue": 31266.46, "upper_bound": 37144.55, "lower_bound": 25388.36}, {"date": "2025-07-19", "predicted_revenue": 25901.14, "upper_bound": 30874.15, "lower_bound": 20928.12}, {"date": "2025-07-20", "predicted_revenue": 15834.73, "upper_bound": 18938.34, "lower_bound": 12731.12}, {"date": "2025-07-21", "predicted_revenue": 18223.22, "upper_bound": 21867.87, "lower_bound": 14578.58}, {"date": "2025-07-22", "predicted_revenue": 19618.36, "upper_bound": 23620.51, "lower_bound": 15616.22}, {"date": "2025-07-23", "predicted_revenue": 22323.76, "upper_bound": 26967.11, "lower_bound": 17680.42}, {"date": "2025-07-24", "predicted_revenue": 35347.04, "upper_bound": 42840.61, "lower_bound": 27853.47}, {"date": "2025-07-25", "predicted_revenue": 38270.46, "upper_bound": 46536.88, "lower_bound": 30004.04}, {"date": "2025-07-26", "predicted_revenue": 27623.57, "upper_bound": 33700.75, "lower_bound": 21546.38}, {"date": "2025-07-27", "predicted_revenue": 16834.46, "upper_bound": 20605.38, "lower_bound": 13063.54}, {"date": "2025-07-28", "predicted_revenue": 18992.42, "upper_bound": 23322.69, "lower_bound": 14662.15}, {"date": "2025-07-29", "predicted_revenue": 22658.14, "upper_bound": 27914.82, "lower_bound": 17401.45}, {"date": "2025-07-30", "predicted_revenue": 23615.89, "upper_bound": 29189.24, "lower_bound": 18042.54}]}, "recent_transactions": [{"transaction_id": "biz_0223-020925", "timestamp": "2024-12-30 22:25:45", "amount_sar": 105.19, "payment_method": "credit_card"}, {"transaction_id": "biz_0223-021008", "timestamp": "2024-12-30 22:28:48", "amount_sar": 11.92, "payment_method": "cash"}, {"transaction_id": "biz_0223-021027", "timestamp": "2024-12-30 22:35:53", "amount_sar": 48.39, "payment_method": "cash"}, {"transaction_id": "biz_0223-021030", "timestamp": "2024-12-30 22:52:53", "amount_sar": 10.67, "payment_method": "mada"}, {"transaction_id": "biz_0223-020976", "timestamp": "2024-12-30 22:58:41", "amount_sar": 30.04, "payment_method": "mada"}, {"transaction_id": "biz_0223-021058", "timestamp": "2024-12-30 23:02:45", "amount_sar": 124.41, "payment_method": "cash"}, {"transaction_id": "biz_0223-020916", "timestamp": "2024-12-30 23:03:28", "amount_sar": 49.59, "payment_method": "mada"}, {"transaction_id": "biz_0223-020999", "timestamp": "2024-12-30 23:27:23", "amount_sar": 66.33, "payment_method": "mada"}, {"transaction_id": "biz_0223-020984", "timestamp": "2024-12-30 23:40:27", "amount_sar": 122.48, "payment_method": "mada"}, {"transaction_id": "biz_0223-021051", "timestamp": "2024-12-30 23:51:13", "amount_sar": 28.77, "payment_method": "cash"}], "energy_trend": [{"date": "2024-12-24", "total_kwh": 158.71, "peak_hour_kwh": 91.26, "off_peak_kwh": 67.45, "energy_efficiency_score": 0.6008}, {"date": "2024-12-25", "total_kwh": 182.14, "peak_hour_kwh": 99.37, "off_peak_kwh": 82.77, "energy_efficiency_score": 0.4889}, {"date": "2024-12-26", "total_kwh": 195.65, "peak_hour_kwh": 127.49, "off_peak_kwh": 68.16, "energy_efficiency_score": 0.8016}, {"date": "2024-12-27", "total_kwh": 211.53, "peak_hour_kwh": 119.43, "off_peak_kwh": 92.1, "energy_efficiency_score": 0.6298}, {"date": "2024-12-28", "total_kwh": 162.48, "peak_hour_kwh": 93.51, "off_peak_kwh": 68.97, "energy_efficiency_score": 0.8882}, {"date": "2024-12-29", "total_kwh": 201.4, "peak_hour_kwh": 132.81, "off_peak_kwh": 68.59, "energy_efficiency_score": 0.6556}, {"date": "2024-12-30", "total_kwh": 163.06, "peak_hour_kwh": 93.52, "off_peak_kwh": 69.54, "energy_efficiency_score": 0.6554}]}