{"business": {"id": "biz_0097", "name": "Turki Market", "type": "b", "sector": "high_freq_mid_ticket_retail", "archetype": "high_freq_mid_ticket_retail", "loan_pipeline": "sme"}, "summary": {"business_id": "biz_0097", "period": "2024-10-01 to 2024-12-30", "total_transactions": 17973, "total_revenue_sar": 1875922.02, "avg_daily_revenue_sar": 20614.53, "avg_daily_transactions": 197.5, "avg_energy_kwh": 179.97, "avg_efficiency_score": 0.677, "green_days": ["2024-10-19", "2024-10-31", "2024-11-07", "2024-11-14", "2024-11-18", "2024-11-19", "2024-12-22"], "payment_method_breakdown": {"mada": 0.5021, "cash": 0.4031, "credit_card": 0.0948}}, "dscr": {"business_id": "biz_0097", "dscr_score": 2.6776, "risk_tier": "very_low", "approved_credit_limit_sar": 2782961.0, "dynamic_credit_limit": {"adjusted_credit_limit": 2782961.0, "trend_direction": "steady", "adjustment_multiplier": 1.0}, "expense_ratio": 0.81, "expense_source": "ai_derived", "archetype_description": "high_freq_mid_ticket_retail", "net_operating_income_sar": 119134.79, "interest_rate_base": 0.065, "final_interest_rate": 0.060000000000000005, "sustainability_eligible": true, "revenue_metrics": {"total_revenue": 1875922.02, "avg_daily_revenue": 20614.53, "revenue_trend": "steady"}, "transition_readiness": {"decision": "approve", "blocking_reasons": [], "gates_passed": ["revenue_verified", "archetype_classified", "dscr_sufficient"], "recommended_pipeline": "sme_loan"}}, "fraud": {"business_id": "biz_0097", "overall_status": "flagged", "fraud_score": 55, "approval_frozen": false, "anomalies": [], "checks_passed": ["amount_range", "hour_pattern", "payment_method"], "reasons": ["Behavioral anomaly detected"]}, "forecast": {"summary": {"trend_direction": "steady", "avg_predicted_revenue": 20614.53, "confidence": 0.582}, "series": [{"date": "2025-07-01", "predicted_revenue": 18383.14, "upper_bound": 20589.12, "lower_bound": 16177.17}, {"date": "2025-07-02", "predicted_revenue": 20561.26, "upper_bound": 23110.86, "lower_bound": 18011.67}, {"date": "2025-07-03", "predicted_revenue": 24798.96, "upper_bound": 27973.23, "lower_bound": 21624.69}, {"date": "2025-07-04", "predicted_revenue": 27439.06, "upper_bound": 31061.01, "lower_bound": 23817.1}, {"date": "2025-07-05", "predicted_revenue": 20215.75, "upper_bound": 22965.09, "lower_bound": 17466.41}, {"date": "2025-07-06", "predicted_revenue": 13697.08, "upper_bound": 15614.67, "lower_bound": 11779.49}, {"date": "2025-07-07", "predicted_revenue": 15263.68, "upper_bound": 17461.65, "lower_bound": 13065.71}, {"date": "2025-07-08", "predicted_revenue": 17670.87, "upper_bound": 20286.16, "lower_bound": 15055.58}, {"date": "2025-07-09", "predicted_revenue": 18657.86, "upper_bound": 21493.86, "lower_bound": 15821.87}, {"date": "2025-07-10", "predicted_revenue": 27040.41, "upper_bound": 31258.71, "lower_bound": 22822.11}, {"date": "2025-07-11", "predicted_revenue": 27380.59, "upper_bound": 31761.48, "lower_bound": 22999.69}, {"date": "2025-07-12", "predicted_revenue": 19952.88, "upper_bound": 23225.15, "lower_bound": 16680.61}, {"date": "2025-07-13", "predicted_revenue": 14465.09, "upper_bound": 16895.23, "lower_bound": 12034.96}, {"date": "2025-07-14", "predicted_revenue": 14822.59, "upper_bound": 17372.08, "lower_bound": 12273.11}, {"date": "2025-07-15", "predicted_revenue": 18768.12, "upper_bound": 22071.31, "lower_bound": 15464.93}, {"date": "2025-07-16", "predicted_revenue": 16603.61, "upper_bound": 19592.26, "lower_bound": 13614.96}, {"date": "2025-07-17", "predicted_revenue": 27082.31, "upper_bound": 32065.45, "lower_bound": 22099.16}, {"date": "2025-07-18", "predicted_revenue": 30935.18, "upper_bound": 36750.99, "lower_bound": 25119.37}, {"date": "2025-07-19", "predicted_revenue": 22817.58, "upper_bound": 27198.55, "lower_bound": 18436.6}, {"date": "2025-07-20", "predicted_revenue": 15522.69, "upper_bound": 18565.14, "lower_bound": 12480.24}, {"date": "2025-07-21", "predicted_revenue": 14936.59, "upper_bound": 17923.91, "lower_bound": 11949.27}, {"date": "2025-07-22", "predicted_revenue": 16513.54, "upper_bound": 19882.3, "lower_bound": 13144.78}, {"date": "2025-07-23", "predicted_revenue": 20591.69, "upper_bound": 24874.77, "lower_bound": 16308.62}, {"date": "2025-07-24", "predicted_revenue": 25097.51, "upper_bound": 30418.18, "lower_bound": 19776.84}, {"date": "2025-07-25", "predicted_revenue": 28472.89, "upper_bound": 34623.04, "lower_bound": 22322.75}, {"date": "2025-07-26", "predicted_revenue": 21011.0, "upper_bound": 25633.42, "lower_bound": 16388.58}, {"date": "2025-07-27", "predicted_revenue": 15588.02, "upper_bound": 19079.74, "lower_bound": 12096.31}, {"date": "2025-07-28", "predicted_revenue": 17526.64, "upper_bound": 21522.72, "lower_bound": 13530.57}, {"date": "2025-07-29", "predicted_revenue": 16237.61, "upper_bound": 20004.74, "lower_bound": 12470.48}, {"date": "2025-07-30", "predicted_revenue": 20392.41, "upper_bound": 25205.02, "lower_bound": 15579.8}]}, "recent_transactions": [{"transaction_id": "biz_0097-017945", "timestamp": "2024-12-30 22:13:13", "amount_sar": 288.51, "payment_method": "mada"}, {"transaction_id": "biz_0097-017956", "timestamp": "2024-12-30 22:32:47", "amount_sar": 435.97, "payment_method": "mada"}, {"transaction_id": "biz_0097-017919", "timestamp": "2024-12-30 22:36:10", "amount_sar": 109.13, "payment_method": "cash"}, {"transaction_id": "biz_0097-017895", "timestamp": "2024-12-30 23:05:34", "amount_sar": 53.28, "payment_method": "credit_card"}, {"transaction_id": "biz_0097-017925", "timestamp": "2024-12-30 23:25:45", "amount_sar": 37.36, "payment_method": "mada"}, {"transaction_id": "biz_0097-017912", "timestamp": "2024-12-30 23:29:18", "amount_sar": 16.91, "payment_method": "mada"}, {"transaction_id": "biz_0097-017953", "timestamp": "2024-12-30 23:30:51", "amount_sar": 157.2, "payment_method": "mada"}, {"transaction_id": "biz_0097-017908", "timestamp": "2024-12-30 23:43:15", "amount_sar": 79.63, "payment_method": "cash"}, {"transaction_id": "biz_0097-017934", "timestamp": "2024-12-30 23:49:57", "amount_sar": 41.76, "payment_method": "cash"}, {"transaction_id": "biz_0097-017922", "timestamp": "2024-12-30 23:51:10", "amount_sar": 25.49, "payment_method": "mada"}], "energy_trend": [{"date": "2024-12-24", "total_kwh": 190.01, "peak_hour_kwh": 99.95, "off_peak_kwh": 90.06, "energy_efficiency_score": 0.7925}, {"date": "2024-12-25", "total_kwh": 179.06, "peak_hour_kwh": 124.03, "off_peak_kwh": 55.03, "energy_efficiency_score": 0.6843}, {"date": "2024-12-26", "total_kwh": 133.73, "peak_hour_kwh": 75.84, "off_peak_kwh": 57.89, "energy_efficiency_score": 0.8425}, {"date": "2024-12-27", "total_kwh": 204.35, "peak_hour_kwh": 139.87, "off_peak_kwh": 64.48, "energy_efficiency_score": 0.4694}, {"date": "2024-12-28", "total_kwh": 200.82, "peak_hour_kwh": 144.04, "off_peak_kwh": 56.78, "energy_efficiency_score": 0.6839}, {"date": "2024-12-29", "total_kwh": 210.0, "peak_hour_kwh": 118.54, "off_peak_kwh": 91.46, "energy_efficiency_score": 0.7113}, {"date": "2024-12-30", "total_kwh": 176.74, "peak_hour_kwh": 120.7, "off_peak_kwh": 56.04, "energy_efficiency_score": 0.5394}]}