{"business": {"id": "biz_0491", "name": "Hana Beauty Studio", "type": "e", "sector": "mid_ticket_mid_freq_services", "archetype": "mid_ticket_mid_freq_services", "loan_pipeline": "sme"}, "summary": {"business_id": "biz_0491", "period": "2024-10-01 to 2024-12-30", "total_transactions": 1379, "total_revenue_sar": 317197.89, "avg_daily_revenue_sar": 3916.02, "avg_daily_transactions": 15.2, "avg_energy_kwh": 41.91, "avg_efficiency_score": 0.6511, "green_days": ["2024-11-14", "2024-12-09"], "payment_method_breakdown": {"mada": 0.6954, "cash": 0.1762, "credit_card": 0.1284}}, "dscr": {"business_id": "biz_0491", "dscr_score": 1.6709, "risk_tier": "low", "approved_credit_limit_sar": 376455.0, "dynamic_credit_limit": {"adjusted_credit_limit": 376455.0, "trend_direction": "steady", "adjustment_multiplier": 1.0}, "expense_ratio": 0.598, "expense_source": "ai_derived", "archetype_description": "mid_ticket_mid_freq_services", "net_operating_income_sar": 42621.29, "interest_rate_base": 0.065, "final_interest_rate": 0.060000000000000005, "sustainability_eligible": true, "revenue_metrics": {"total_revenue": 317197.89, "avg_daily_revenue": 3916.02, "revenue_trend": "steady"}, "transition_readiness": {"decision": "approve", "blocking_reasons": [], "gates_passed": ["revenue_verified", "archetype_classified", "dscr_sufficient"], "recommended_pipeline": "sme_loan"}}, "fraud": {"business_id": "biz_0491", "overall_status": "flagged", "fraud_score": 36, "approval_frozen": false, "anomalies": [], "checks_passed": ["amount_range", "hour_pattern", "payment_method"], "reasons": ["Behavioral anomaly detected"]}, "forecast": {"summary": {"trend_direction": "steady", "avg_predicted_revenue": 3916.02, "confidence": 0.4124}, "series": [{"date": "2025-07-01", "predicted_revenue": 4452.07, "upper_bound": 4986.31, "lower_bound": 3917.82}, {"date": "2025-07-02", "predicted_revenue": 4182.08, "upper_bound": 4700.65, "lower_bound": 3663.5}, {"date": "2025-07-03", "predicted_revenue": 2934.18, "upper_bound": 3309.76, "lower_bound": 2558.61}, {"date": "2025-07-04", "predicted_revenue": 2014.3, "upper_bound": 2280.18, "lower_bound": 1748.41}, {"date": "2025-07-05", "predicted_revenue": 3545.87, "upper_bound": 4028.11, "lower_bound": 3063.63}, {"date": "2025-07-06", "predicted_revenue": 3979.04, "upper_bound": 4536.1, "lower_bound": 3421.97}, {"date": "2025-07-07", "predicted_revenue": 3676.5, "upper_bound": 4205.92, "lower_bound": 3147.08}, {"date": "2025-07-08", "predicted_revenue": 4210.39, "upper_bound": 4833.53, "lower_bound": 3587.25}, {"date": "2025-07-09", "predicted_revenue": 4502.59, "upper_bound": 5186.98, "lower_bound": 3818.2}, {"date": "2025-07-10", "predicted_revenue": 3237.17, "upper_bound": 3742.17, "lower_bound": 2732.17}, {"date": "2025-07-11", "predicted_revenue": 2085.25, "upper_bound": 2418.89, "lower_bound": 1751.61}, {"date": "2025-07-12", "predicted_revenue": 3779.62, "upper_bound": 4399.47, "lower_bound": 3159.76}, {"date": "2025-07-13", "predicted_revenue": 4366.94, "upper_bound": 5100.58, "lower_bound": 3633.29}, {"date": "2025-07-14", "predicted_revenue": 4039.09, "upper_bound": 4733.81, "lower_bound": 3344.37}, {"date": "2025-07-15", "predicted_revenue": 4794.82, "upper_bound": 5638.71, "lower_bound": 3950.93}, {"date": "2025-07-16", "predicted_revenue": 4596.84, "upper_bound": 5424.27, "lower_bound": 3769.41}, {"date": "2025-07-17", "predicted_revenue": 3188.34, "upper_bound": 3775.0, "lower_bound": 2601.69}, {"date": "2025-07-18", "predicted_revenue": 2080.44, "upper_bound": 2471.56, "lower_bound": 1689.31}, {"date": "2025-07-19", "predicted_revenue": 3520.42, "upper_bound": 4196.35, "lower_bound": 2844.5}, {"date": "2025-07-20", "predicted_revenue": 4505.7, "upper_bound": 5388.81, "lower_bound": 3622.58}, {"date": "2025-07-21", "predicted_revenue": 4223.47, "upper_bound": 5068.16, "lower_bound": 3378.77}, {"date": "2025-07-22", "predicted_revenue": 4265.79, "upper_bound": 5136.01, "lower_bound": 3395.57}, {"date": "2025-07-23", "predicted_revenue": 4452.24, "upper_bound": 5378.31, "lower_bound": 3526.18}, {"date": "2025-07-24", "predicted_revenue": 2746.5, "upper_bound": 3328.75, "lower_bound": 2164.24}, {"date": "2025-07-25", "predicted_revenue": 1896.03, "upper_bound": 2305.57, "lower_bound": 1486.48}, {"date": "2025-07-26", "predicted_revenue": 3624.19, "upper_bound": 4421.52, "lower_bound": 2826.87}, {"date": "2025-07-27", "predicted_revenue": 4456.92, "upper_bound": 5455.27, "lower_bound": 3458.57}, {"date": "2025-07-28", "predicted_revenue": 3979.86, "upper_bound": 4887.27, "lower_bound": 3072.46}, {"date": "2025-07-29", "predicted_revenue": 4544.91, "upper_bound": 5599.33, "lower_bound": 3490.49}, {"date": "2025-07-30", "predicted_revenue": 4433.77, "upper_bound": 5480.14, "lower_bound": 3387.4}]}, "recent_transactions": [{"transaction_id": "biz_0491-001377", "timestamp": "2024-12-30 11:54:01", "amount_sar": 145.64, "payment_method": "mada"}, {"transaction_id": "biz_0491-001379", "timestamp": "2024-12-30 12:03:16", "amount_sar": 255.08, "payment_method": "mada"}, {"transaction_id": "biz_0491-001373", "timestamp": "2024-12-30 12:26:09", "amount_sar": 88.19, "payment_method": "mada"}, {"transaction_id": "biz_0491-001368", "timestamp": "2024-12-30 12:46:36", "amount_sar": 159.15, "payment_method": "mada"}, {"transaction_id": "biz_0491-001374", "timestamp": "2024-12-30 13:31:00", "amount_sar": 238.26, "payment_method": "mada"}, {"transaction_id": "biz_0491-001376", "timestamp": "2024-12-30 15:03:42", "amount_sar": 265.03, "payment_method": "credit_card"}, {"transaction_id": "biz_0491-001371", "timestamp": "2024-12-30 16:08:56", "amount_sar": 178.59, "payment_method": "mada"}, {"transaction_id": "biz_0491-001369", "timestamp": "2024-12-30 16:33:31", "amount_sar": 170.79, "payment_method": "cash"}, {"transaction_id": "biz_0491-001370", "timestamp": "2024-12-30 19:26:03", "amount_sar": 265.17, "payment_method": "cash"}, {"transaction_id": "biz_0491-001375", "timestamp": "2024-12-30 19:35:18", "amount_sar": 219.09, "payment_method": "cash"}], "energy_trend": [{"date": "2024-12-24", "total_kwh": 46.12, "peak_hour_kwh": 23.34, "off_peak_kwh": 22.78, "energy_efficiency_score": 0.6924}, {"date": "2024-12-25", "total_kwh": 34.12, "peak_hour_kwh": 21.26, "off_peak_kwh": 12.86, "energy_efficiency_score": 0.5532}, {"date": "2024-12-26", "total_kwh": 30.62, "peak_hour_kwh": 20.57, "off_peak_kwh": 10.05, "energy_efficiency_score": 0.6789}, {"date": "2024-12-27", "total_kwh": 53.32, "peak_hour_kwh": 34.5, "off_peak_kwh": 18.82, "energy_efficiency_score": 0.6518}, {"date": "2024-12-28", "total_kwh": 45.09, "peak_hour_kwh": 29.11, "off_peak_kwh": 15.98, "energy_efficiency_score": 0.6159}, {"date": "2024-12-29", "total_kwh": 35.41, "peak_hour_kwh": 22.26, "off_peak_kwh": 13.15, "energy_efficiency_score": 0.6271}, {"date": "2024-12-30", "total_kwh": 47.92, "peak_hour_kwh": 33.71, "off_peak_kwh": 14.21, "energy_efficiency_score": 0.8065}]}