{"business": {"id": "biz_0142", "name": "Rawabi Grill", "type": "a", "sector": "high_freq_low_ticket_food", "archetype": "high_freq_low_ticket_food", "loan_pipeline": "sme"}, "summary": {"business_id": "biz_0142", "period": "2024-10-01 to 2024-12-30", "total_transactions": 8366, "total_revenue_sar": 250118.08, "avg_daily_revenue_sar": 2779.09, "avg_daily_transactions": 91.9, "avg_energy_kwh": 91.67, "avg_efficiency_score": 0.6365, "green_days": ["2024-11-08", "2024-11-23", "2024-12-16"], "payment_method_breakdown": {"mada": 0.6587, "cash": 0.196, "credit_card": 0.1452}}, "dscr": {"business_id": "biz_0142", "dscr_score": 0.951, "risk_tier": "critical", "approved_credit_limit_sar": 0.0, "dynamic_credit_limit": {"adjusted_credit_limit": 0.0, "trend_direction": "steady", "adjustment_multiplier": 1.0}, "expense_ratio": 0.77, "expense_source": "ai_derived", "archetype_description": "high_freq_low_ticket_food", "net_operating_income_sar": 19228.4, "interest_rate_base": 0.065, "final_interest_rate": 0.060000000000000005, "sustainability_eligible": true, "revenue_metrics": {"total_revenue": 250118.08, "avg_daily_revenue": 2779.09, "revenue_trend": "steady"}, "transition_readiness": {"decision": "decline", "blocking_reasons": ["DSCR or fraud threshold not met"], "gates_passed": ["revenue_verified", "archetype_classified"], "recommended_pipeline": "monitor"}}, "fraud": {"business_id": "biz_0142", "overall_status": "clean", "fraud_score": 0, "approval_frozen": false, "anomalies": [], "checks_passed": ["amount_range", "hour_pattern", "payment_method"], "reasons": []}, "forecast": {"summary": {"trend_direction": "steady", "avg_predicted_revenue": 2779.09, "confidence": 0.4381}, "series": [{"date": "2025-07-01", "predicted_revenue": 2705.54, "upper_bound": 3030.21, "lower_bound": 2380.88}, {"date": "2025-07-02", "predicted_revenue": 2581.25, "upper_bound": 2901.33, "lower_bound": 2261.18}, {"date": "2025-07-03", "predicted_revenue": 3613.67, "upper_bound": 4076.22, "lower_bound": 3151.12}, {"date": "2025-07-04", "predicted_revenue": 3580.52, "upper_bound": 4053.15, "lower_bound": 3107.89}, {"date": "2025-07-05", "predicted_revenue": 3144.51, "upper_bound": 3572.16, "lower_bound": 2716.86}, {"date": "2025-07-06", "predicted_revenue": 1489.11, "upper_bound": 1697.59, "lower_bound": 1280.64}, {"date": "2025-07-07", "predicted_revenue": 2311.61, "upper_bound": 2644.49, "lower_bound": 1978.74}, {"date": "2025-07-08", "predicted_revenue": 2383.2, "upper_bound": 2735.92, "lower_bound": 2030.49}, {"date": "2025-07-09", "predicted_revenue": 2736.91, "upper_bound": 3152.92, "lower_bound": 2320.9}, {"date": "2025-07-10", "predicted_revenue": 3470.28, "upper_bound": 4011.65, "lower_bound": 2928.92}, {"date": "2025-07-11", "predicted_revenue": 3282.66, "upper_bound": 3807.88, "lower_bound": 2757.43}, {"date": "2025-07-12", "predicted_revenue": 3228.22, "upper_bound": 3757.64, "lower_bound": 2698.79}, {"date": "2025-07-13", "predicted_revenue": 1387.58, "upper_bound": 1620.69, "lower_bound": 1154.46}, {"date": "2025-07-14", "predicted_revenue": 2365.12, "upper_bound": 2771.92, "lower_bound": 1958.32}, {"date": "2025-07-15", "predicted_revenue": 2351.12, "upper_bound": 2764.92, "lower_bound": 1937.32}, {"date": "2025-07-16", "predicted_revenue": 2673.99, "upper_bound": 3155.31, "lower_bound": 2192.67}, {"date": "2025-07-17", "predicted_revenue": 3409.49, "upper_bound": 4036.84, "lower_bound": 2782.15}, {"date": "2025-07-18", "predicted_revenue": 3604.11, "upper_bound": 4281.68, "lower_bound": 2926.54}, {"date": "2025-07-19", "predicted_revenue": 3122.09, "upper_bound": 3721.53, "lower_bound": 2522.65}, {"date": "2025-07-20", "predicted_revenue": 1594.65, "upper_bound": 1907.2, "lower_bound": 1282.1}, {"date": "2025-07-21", "predicted_revenue": 2298.24, "upper_bound": 2757.89, "lower_bound": 1838.59}, {"date": "2025-07-22", "predicted_revenue": 2359.13, "upper_bound": 2840.39, "lower_bound": 1877.87}, {"date": "2025-07-23", "predicted_revenue": 2890.2, "upper_bound": 3491.36, "lower_bound": 2289.03}, {"date": "2025-07-24", "predicted_revenue": 3399.27, "upper_bound": 4119.91, "lower_bound": 2678.62}, {"date": "2025-07-25", "predicted_revenue": 3610.48, "upper_bound": 4390.35, "lower_bound": 2830.62}, {"date": "2025-07-26", "predicted_revenue": 2714.16, "upper_bound": 3311.27, "lower_bound": 2117.04}, {"date": "2025-07-27", "predicted_revenue": 1647.93, "upper_bound": 2017.06, "lower_bound": 1278.79}, {"date": "2025-07-28", "predicted_revenue": 2178.6, "upper_bound": 2675.33, "lower_bound": 1681.88}, {"date": "2025-07-29", "predicted_revenue": 2510.57, "upper_bound": 3093.02, "lower_bound": 1928.12}, {"date": "2025-07-30", "predicted_revenue": 2935.07, "upper_bound": 3627.75, "lower_bound": 2242.4}]}, "recent_transactions": [{"transaction_id": "biz_0142-008316", "timestamp": "2024-12-30 19:07:28", "amount_sar": 22.14, "payment_method": "cash"}, {"transaction_id": "biz_0142-008313", "timestamp": "2024-12-30 19:28:50", "amount_sar": 38.78, "payment_method": "cash"}, {"transaction_id": "biz_0142-008343", "timestamp": "2024-12-30 19:46:05", "amount_sar": 33.18, "payment_method": "mada"}, {"transaction_id": "biz_0142-008281", "timestamp": "2024-12-30 19:47:41", "amount_sar": 14.92, "payment_method": "mada"}, {"transaction_id": "biz_0142-008354", "timestamp": "2024-12-30 19:51:47", "amount_sar": 25.72, "payment_method": "mada"}, {"transaction_id": "biz_0142-008298", "timestamp": "2024-12-30 20:29:40", "amount_sar": 25.48, "payment_method": "credit_card"}, {"transaction_id": "biz_0142-008338", "timestamp": "2024-12-30 20:43:47", "amount_sar": 33.11, "payment_method": "credit_card"}, {"transaction_id": "biz_0142-008282", "timestamp": "2024-12-30 20:51:53", "amount_sar": 18.65, "payment_method": "mada"}, {"transaction_id": "biz_0142-008294", "timestamp": "2024-12-30 21:40:16", "amount_sar": 26.08, "payment_method": "mada"}, {"transaction_id": "biz_0142-008336", "timestamp": "2024-12-30 23:29:48", "amount_sar": 41.95, "payment_method": "credit_card"}], "energy_trend": [{"date": "2024-12-24", "total_kwh": 78.27, "peak_hour_kwh": 39.19, "off_peak_kwh": 39.08, "energy_efficiency_score": 0.771}, {"date": "2024-12-25", "total_kwh": 83.16, "peak_hour_kwh": 56.52, "off_peak_kwh": 26.64, "energy_efficiency_score": 0.7538}, {"date": "2024-12-26", "total_kwh": 95.42, "peak_hour_kwh": 52.25, "off_peak_kwh": 43.17, "energy_efficiency_score": 0.762}, {"date": "2024-12-27", "total_kwh": 90.34, "peak_hour_kwh": 47.64, "off_peak_kwh": 42.7, "energy_efficiency_score": 0.5824}, {"date": "2024-12-28", "total_kwh": 89.95, "peak_hour_kwh": 54.28, "off_peak_kwh": 35.67, "energy_efficiency_score": 0.4083}, {"date": "2024-12-29", "total_kwh": 88.66, "peak_hour_kwh": 56.37, "off_peak_kwh": 32.29, "energy_efficiency_score": 0.7154}, {"date": "2024-12-30", "total_kwh": 89.61, "peak_hour_kwh": 46.66, "off_peak_kwh": 42.95, "energy_efficiency_score": 0.5176}]}